osdi/__init__.py
osdi/action_builder/__init__.py
osdi/action_builder/model.py
osdi/action_builder/person.py
osdi/action_builder/service.py
osdi/action_builder/tag.py
osdi/action_network/__init__.py
osdi/action_network/person.py
osdi/action_network/service.py
osdi/action_network/tag.py
osdi/base/__init__.py
osdi/base/model.py
osdi/base/service.py
osdi/base/utils.py
osdi-0.3.1.dist-info/WHEEL
osdi-0.3.1.dist-info/METADATA
osdi-0.3.1.dist-info/RECORD
